{"songs": [{"title": "Animals", "album": "The 2nd Law", "year": "2013-04-20", "lyrics": "[Verse 1]\nAnimal\nYou\u2019re an animal\nDon\u2019t take anything less\nOut of control\nYou\u2019re out of control\nStrike those in distress\n\n[Hook 1]\nAnalyse\nAdvertise\nExpand\nBend more rules\nBuy yourself an island\n\n[Verse 2]\nAnimals\nWe\u2019re animals\nBuy when blood is on the street\nOut of control\nWe\u2019re out of control\nCrush those who beg at your feet\n\n[Hook 2]\nAnalyse\nFranchise\nSpread out\nKill the competition\nAnd buy yourself an ocean\n\n[Hook 3]\nAmortise\nDownsize\nLay off\nKill yourself\nCome on and do us all a favour\n\n[Instumental]", "image": "https://images.genius.com/e00c2cd9627558026a8fe51f598f0604.1000x1000x1.jpg"}], "artist": "Muse"}