{"songs": [{"title": "New Kind Of Kick", "album": null, "year": "2016-10-28", "lyrics": "[Verse 1]\nLife is short\nFilled with stuff\nI don't know what for\nI ain't had enough\nI learned all I know\nBy the age of nine\nBut I could better myself\nIf I could only find\n\n[Chorus]\nSome new kind of kick\nSomething I ain't have\nSome new kind of buzz\nLike on a go hog mad\nI'm looking, I'm looking, I'm looking for\nSomething I ain't had before\nI'm looking, I'm looking, I'm looking, I'm looking to find\nSome new kind of kick\nSome new kind of kick\nGive me a kick, kick\nI want some new kind of kick\n\n[Verse 2]\nLike baby needs mom\nLike Susie needs dick\nThis baby needs...\n\n[Chorus]\nSome new kind of kick\nI want some new kind of kick\nSome new kind of kick\nSome new kind of kick\nI want some new kind of kick\nI'm looking, I'm looking, I'm looking for\nSomething I ain't had before\nI'm looking, I'm looking, I'm looking, I'm looking to find\nSome new kind of kick\nSome new kind of kick\nSome new kind of kick\nI want some new kind of kick\nSome new kind of kick", "image": "https://images.genius.com/dba4cf81e0a6e7963be216f41c10f730.519x519x1.jpg"}], "artist": "Muse"}